daimin_data/__init__.py
daimin_data/_modidx.py
daimin_data/core.py
daimin_data-0.0.3.dist-info/LICENSE
daimin_data-0.0.3.dist-info/METADATA
daimin_data-0.0.3.dist-info/WHEEL
daimin_data-0.0.3.dist-info/entry_points.txt
daimin_data-0.0.3.dist-info/top_level.txt
daimin_data-0.0.3.dist-info/RECORD
